marshmallow_dataclass/__init__.py
marshmallow_dataclass/collection_field.py
marshmallow_dataclass/lazy_class_attribute.py
marshmallow_dataclass/mypy.py
marshmallow_dataclass/py.typed
marshmallow_dataclass/typing.py
marshmallow_dataclass/union_field.py
marshmallow_dataclass-8.7.0.dist-info/LICENSE
marshmallow_dataclass-8.7.0.dist-info/METADATA
marshmallow_dataclass-8.7.0.dist-info/WHEEL
marshmallow_dataclass-8.7.0.dist-info/top_level.txt
marshmallow_dataclass-8.7.0.dist-info/RECORD
